LICENSE
MANIFEST.in
README.md
pyproject.toml
requirements.txt
setup.cfg
setup.py
test_requirements.txt
version.txt
cast_ai_se_cli.egg-info/PKG-INFO
cast_ai_se_cli.egg-info/SOURCES.txt
cast_ai_se_cli.egg-info/dependency_links.txt
cast_ai_se_cli.egg-info/entry_points.txt
cast_ai_se_cli.egg-info/requires.txt
cast_ai_se_cli.egg-info/top_level.txt
cli/__init__.py
cli/config_constants.py
cli/constants.py
cli/shell.py
cli/models/__init__.py
cli/models/config.py
cli/models/demo_cfg.py
cli/models/timed_text.py
cli/orchestrators/__init__.py
cli/orchestrators/audit_orch.py
cli/orchestrators/base_orch.py
cli/orchestrators/demo_orch.py
cli/orchestrators/snapshot_orch.py
cli/services/__init__.py
cli/services/general_responder_svc.py
cli/services/misc_svc.py
cli/services/validators.py
cli/services/version_svc.py
tests/__init__.py
venv/Lib/site-packages/numpy/core/lib/npy-pkg-config/mlib.ini
venv/Lib/site-packages/numpy/core/lib/npy-pkg-config/npymath.ini
venv/Lib/site-packages/numpy/typing/tests/data/mypy.ini