Metadata-Version: 2.1
Name: cast-ai-se-cli
Version: 0.0.24
Summary: Provides a CLI to run all sorts of sequences like demo prep.
Author: Dan Amzulescu
Author-email: dan@cast.ai
Keywords: cast command-line cli
Classifier: Development Status :: 4 - Beta
Classifier: Topic :: Software Development :: User Interfaces
Classifier: License :: OSI Approved :: Apache Software License
Requires-Python: >=3.11
License-File: LICENSE
Requires-Dist: python-dotenv==1.0.0
Requires-Dist: requests==2.31.0
Requires-Dist: boto3==1.33.10
Requires-Dist: yaspin==3.0.1
Requires-Dist: docopt-ng==0.9.0
Requires-Dist: cast-ai-se-tools==0.0.63
Requires-Dist: regex==2023.10.3
Requires-Dist: yolk==0.4.3
Requires-Dist: requests==2.31.0
Requires-Dist: packaging==24.0
